km3irf/__init__.py
km3irf/build_irf.py
km3irf/interpolation.py
km3irf/irf_tools.py
km3irf/psf_3d.py
km3irf/psf_table.py
km3irf/test_utils.py
km3irf/utils.py
km3irf/version.py
km3irf/data/aeff.fits
km3irf/data/aeff_nocuts.fits
km3irf/data/bkg_mu.fits
km3irf/data/bkg_nu.fits
km3irf/data/bkg_nu_knee_correction_test.fits
km3irf/data/edisp.fits
km3irf/data/edisp_no_norm.fits
km3irf/data/edisp_no_smooth_no_norm.fits
km3irf/data/psf.fits
km3irf/data/psf_no_norm.fits
km3irf/data/psf_no_smooth_no_norm.fits
km3irf/data/test_10events.dst.root
km3irf-0.4.0.dist-info/LICENSE
km3irf-0.4.0.dist-info/METADATA
km3irf-0.4.0.dist-info/WHEEL
km3irf-0.4.0.dist-info/top_level.txt
km3irf-0.4.0.dist-info/RECORD
